gowork/__init__.py
gowork/databases.py
gowork/handler.py
gowork/monitor.py
gowork/safe/__init__.py
gowork/safe/configs.py
gowork-1.0.2.post1.dist-info/METADATA
gowork-1.0.2.post1.dist-info/WHEEL
gowork-1.0.2.post1.dist-info/top_level.txt
gowork-1.0.2.post1.dist-info/RECORD
