Metadata-Version: 2.1
Name: gowork
Version: 1.0.2.post1
Summary: Library to help track your credentials and database engines
Home-page: https://github.com/Phomint/GoWork
Author: Patrick Amaral
Author-email: patrick.dev.atom@gmail.com
License: GPLv3
Keywords: databases,athena,mysql,mongodb
Classifier: Programming Language :: Python :: 3
Classifier: License :: OSI Approved :: GNU General Public License v3 (GPLv3)
Classifier: Operating System :: OS Independent
Requires-Python: >=3.6
Requires-Dist: numpy
Requires-Dist: pandas
Requires-Dist: pyathena
Requires-Dist: pymysql
Requires-Dist: glob2
Requires-Dist: sqlalchemy
Requires-Dist: mongudb
